{
    "baseUrl": "http://localhost:3000/",
    "screenshotsFolder": "cypress/report/assets",
    "screenshotOnRunFailure": true,
    "videoCompression": false,
    "reporter": "cypress-multi-reporters",
    "reporterOptions": {
        "reporterEnabled": "mochawesome",
        "mochawesomeReporterOptions": {
            "reportDir": "mochawesome-report",
            "overwrite": false,
            "reportFilename": "index.html",
            "html": true,
            "json": false
        }
    }
}

